policy_weaver-0.3.9.dist-info/licenses/LICENSE
policyweaver/__init__.py
policyweaver/weaver.py
policyweaver/core/__init__.py
policyweaver/core/auth.py
policyweaver/core/common.py
policyweaver/core/conf.py
policyweaver/core/enum.py
policyweaver/core/exception.py
policyweaver/core/utility.py
policyweaver/core/api/__init__.py
policyweaver/core/api/fabric.py
policyweaver/core/api/microsoftgraph.py
policyweaver/core/api/rest.py
policyweaver/models/__init__.py
policyweaver/models/common.py
policyweaver/models/config.py
policyweaver/models/export.py
policyweaver/models/fabric.py
policyweaver/plugins/__init__.py
policyweaver/plugins/databricks/__init__.py
policyweaver/plugins/databricks/api.py
policyweaver/plugins/databricks/client.py
policyweaver/plugins/databricks/model.py
policyweaver/plugins/snowflake/__init__.py
policyweaver/plugins/snowflake/api.py
policyweaver/plugins/snowflake/client.py
policyweaver/plugins/snowflake/model.py
policy_weaver-0.3.9.dist-info/METADATA
policy_weaver-0.3.9.dist-info/WHEEL
policy_weaver-0.3.9.dist-info/top_level.txt
policy_weaver-0.3.9.dist-info/RECORD
