Metadata-Version: 2.4
Name: policy-weaver
Version: 0.3.9
Summary: Policy Weaver for Microsoft Fabric
Author-email: Tonio Lora <tonio.lora@microsoft.com>, Melissa Lacefield <melilace@microsoft.com>, Emily Nguyen <Emily.Nguyen@microsoft.com>, Andreas J Rederer <andreas.rederer@microsoft.com>
Project-URL: Homepage, https://github.com/microsoft/Policy-Weaver
Project-URL: Documentation, https://github.com/microsoft/Policy-Weaver/blob/main/docs/PolicyWeaver.md
Project-URL: Repository, https://github.com/microsoft/Policy-Weaver.git
Project-URL: Issues, https://github.com/microsoft/Policy-Weaver/issues
Keywords: Fabric,Fabric Access Policy,Databricks,BigQuery,Snowflake
Classifier: Development Status :: 4 - Beta
Classifier: Intended Audience :: Developers
Classifier: Intended Audience :: Information Technology
Classifier: Intended Audience :: System Administrators
Classifier: Topic :: Software Development
Classifier: License :: OSI Approved :: MIT License
Classifier: Programming Language :: Python
Classifier: Programming Language :: Python :: 3
Classifier: Programming Language :: Python :: 3.8
Classifier: Programming Language :: Python :: 3.9
Classifier: Programming Language :: Python :: 3.10
Classifier: Programming Language :: Python :: 3.11
Classifier: Programming Language :: Python :: 3.12
Requires-Python: >=3.11.8
License-File: LICENSE
Requires-Dist: azure-identity>=1.19.0
Requires-Dist: azure-storage-file-datalake>=12.18.1
Requires-Dist: databricks-sdk>=0.57.0
Requires-Dist: msgraph-sdk>=1.16.0
Requires-Dist: pydantic>=2.10.5
Requires-Dist: python-dotenv>=1.0.1
Requires-Dist: pyyaml>=6.0.2
Requires-Dist: snowflake-connector-python>=3.16.0
Provides-Extra: dev
Requires-Dist: ruff==0.7.1; extra == "dev"
Requires-Dist: sphinx>=7.1.2; extra == "dev"
Dynamic: license-file
